clean_textify/__init__.py
clean_textify/clean_textify.py
cleantextify_neal-0.1.0.dist-info/licenses/LICENSE
cleantextify_neal-0.1.0.dist-info/METADATA
cleantextify_neal-0.1.0.dist-info/WHEEL
cleantextify_neal-0.1.0.dist-info/top_level.txt
cleantextify_neal-0.1.0.dist-info/RECORD
