Metadata-Version: 2.4
Name: cleantextify-neal
Version: 0.1.0
Summary: A lightweight text preprocessing tool for NLP
Home-page: https://github.com/Neal-Salian/clean-textify
Author: Neal Salian
Author-email: nealsalian4@gmail.com
Classifier: Programming Language :: Python :: 3
Classifier: License :: OSI Approved :: MIT License
Classifier: Operating System :: OS Independent
Requires-Python: >=3.7
License-File: LICENSE
Dynamic: author
Dynamic: author-email
Dynamic: classifier
Dynamic: description
Dynamic: description-content-type
Dynamic: home-page
Dynamic: license-file
Dynamic: requires-python
Dynamic: summary
